hotstuff/__init__.py
hotstuff/apis/__init__.py
hotstuff/apis/exchange.py
hotstuff/apis/info.py
hotstuff/apis/subscription.py
hotstuff/methods/__init__.py
hotstuff/methods/exchange/__init__.py
hotstuff/methods/exchange/account.py
hotstuff/methods/exchange/collateral.py
hotstuff/methods/exchange/op_codes.py
hotstuff/methods/exchange/trading.py
hotstuff/methods/exchange/vault.py
hotstuff/methods/info/__init__.py
hotstuff/methods/info/account.py
hotstuff/methods/info/explorer.py
hotstuff/methods/info/global.py
hotstuff/methods/info/vault.py
hotstuff/methods/subscription/__init__.py
hotstuff/methods/subscription/global.py
hotstuff/transports/__init__.py
hotstuff/transports/http.py
hotstuff/transports/websocket.py
hotstuff/types/__init__.py
hotstuff/types/clients.py
hotstuff/types/exchange.py
hotstuff/types/transports.py
hotstuff/utils/__init__.py
hotstuff/utils/address.py
hotstuff/utils/endpoints.py
hotstuff/utils/nonce.py
hotstuff/utils/signing.py
hotstuff_python_sdk-0.0.1b2.dist-info/LICENSE
hotstuff_python_sdk-0.0.1b2.dist-info/METADATA
hotstuff_python_sdk-0.0.1b2.dist-info/WHEEL
hotstuff_python_sdk-0.0.1b2.dist-info/RECORD
