Metadata-Version: 2.3
Name: hotstuff-python-sdk
Version: 0.0.1b2
Summary: Python SDK for interacting with Hotstuff L1
License: MIT
Keywords: hotstuff,trading,blockchain,defi,exchange
Author: hotstuff
Requires-Python: >=3.8,<4.0
Classifier: Development Status :: 4 - Beta
Classifier: Intended Audience :: Developers
Classifier: License :: OSI Approved :: MIT License
Classifier: Programming Language :: Python :: 3
Classifier: Programming Language :: Python :: 3.8
Classifier: Programming Language :: Python :: 3.9
Classifier: Programming Language :: Python :: 3.10
Classifier: Programming Language :: Python :: 3.11
Classifier: Programming Language :: Python :: 3.12
Classifier: Programming Language :: Python :: 3.13
Classifier: Topic :: Software Development :: Libraries :: Python Modules
Requires-Dist: aiohttp (>=3.9.0,<4.0.0)
Requires-Dist: eth-account (>=0.11.0,<0.12.0)
Requires-Dist: eth-utils (>=4.0.0,<5.0.0)
Requires-Dist: msgpack (>=1.0.0,<2.0.0)
Requires-Dist: pydantic (>=2.0.0,<3.0.0)
Requires-Dist: web3 (>=6.0.0,<7.0.0)
Requires-Dist: websockets (>=12.0,<13.0)
Project-URL: Homepage, https://github.com/hotstuff-labs/python-sdk
Project-URL: Repository, https://github.com/hotstuff-labs/python-sdk
